tvnotipy/__about__.py
tvnotipy/__init__.py
tvnotipy/main.py
tvnotipy/config/constants.py
tvnotipy/config/getters.py
tvnotipy/utils/helpers.py
tvnotipy-1.0.1.dist-info/METADATA
tvnotipy-1.0.1.dist-info/WHEEL
tvnotipy-1.0.1.dist-info/entry_points.txt
tvnotipy-1.0.1.dist-info/licenses/LICENSE.txt
tvnotipy-1.0.1.dist-info/RECORD
