Metadata-Version: 2.3
Name: tvnotipy
Version: 1.0.1
Summary: python script for checking if there are new seasons for a list of TV series
Project-URL: Documentation, https://github.com/laszloszurok/tvnotipy#readme
Project-URL: Issues, https://github.com/laszloszurok/tvnotipy/issues
Project-URL: Source, https://github.com/laszloszurok/tvnotipy
Author-email: László Szurok <48314396+laszloszurok@users.noreply.github.com>
License-Expression: MIT
License-File: LICENSE.txt
Classifier: Development Status :: 4 - Beta
Classifier: Programming Language :: Python
Classifier: Programming Language :: Python :: 3.7
Classifier: Programming Language :: Python :: 3.8
Classifier: Programming Language :: Python :: 3.9
Classifier: Programming Language :: Python :: 3.10
Classifier: Programming Language :: Python :: 3.11
Classifier: Programming Language :: Python :: Implementation :: CPython
Classifier: Programming Language :: Python :: Implementation :: PyPy
Requires-Python: >=3.7
Requires-Dist: beautifulsoup4
Requires-Dist: dbus-python
Requires-Dist: requests
